emmett_rest/__init__.py
emmett_rest/__version__.py
emmett_rest/ext.py
emmett_rest/helpers.py
emmett_rest/parsers.py
emmett_rest/rest.py
emmett_rest/serializers.py
emmett_rest/typing.py
emmett_rest/wrappers.py
emmett_rest/openapi/__init__.py
emmett_rest/openapi/api.py
emmett_rest/openapi/generation.py
emmett_rest/openapi/helpers.py
emmett_rest/openapi/mod.py
emmett_rest/openapi/schemas.py
emmett_rest/openapi/assets/__init__.py
emmett_rest/openapi/assets/description.md
emmett_rest/openapi/assets/stoplight.html
emmett_rest/queries/__init__.py
emmett_rest/queries/errors.py
emmett_rest/queries/helpers.py
emmett_rest/queries/parser.py
emmett_rest/queries/validation.py
emmett_rest-1.6.0.dist-info/METADATA
emmett_rest-1.6.0.dist-info/WHEEL
emmett_rest-1.6.0.dist-info/licenses/LICENSE
emmett_rest-1.6.0.dist-info/RECORD
